hawking_proto/hawking_pb2.py
hawking_proto/hawking_pb2_grpc.py
hawking_proto-0.1.15.dist-info/LICENSE
hawking_proto-0.1.15.dist-info/METADATA
hawking_proto-0.1.15.dist-info/WHEEL
hawking_proto-0.1.15.dist-info/top_level.txt
hawking_proto-0.1.15.dist-info/RECORD
